gitlike_commands/__init__.py
gitlike_commands-0.3.0.dist-info/LICENSE
gitlike_commands-0.3.0.dist-info/METADATA
gitlike_commands-0.3.0.dist-info/WHEEL
gitlike_commands-0.3.0.dist-info/RECORD
