Metadata-Version: 2.1
Name: gitlike-commands
Version: 0.3.0
Summary: Makes driver scripts that enable git-like commands so that foo bar will run foo-bar
Home-page: https://github.com/unixorn/gitlike-commands
License: Apache-2.0
Author: Joe Block
Author-email: jpb@unixorn.net
Requires-Python: >=3.9,<4.0
Classifier: License :: OSI Approved :: Apache Software License
Classifier: Programming Language :: Python :: 3
Classifier: Programming Language :: Python :: 3.9
Classifier: Programming Language :: Python :: 3.10
Classifier: Programming Language :: Python :: 3.11
Classifier: Programming Language :: Python :: 3.12
Classifier: Topic :: Software Development :: Libraries :: Python Modules
Classifier: Topic :: System :: System Shells
Project-URL: Bug Tracker, https://github.com/unixorn/gitlike-commands/issues
Project-URL: Repository, https://github.com/unixorn/gitlike-commands
